tempSensor/__init__.py
tempSensor/tempSensor.py
fake_therm_w1_slave_tvanroon-0.3.dist-info/LICENSE
fake_therm_w1_slave_tvanroon-0.3.dist-info/METADATA
fake_therm_w1_slave_tvanroon-0.3.dist-info/WHEEL
fake_therm_w1_slave_tvanroon-0.3.dist-info/top_level.txt
fake_therm_w1_slave_tvanroon-0.3.dist-info/RECORD
