Metadata-Version: 2.1
Name: fake-therm-w1-slave-tvanroon
Version: 0.3
Summary: fake_therm_w1_slave
Home-page: https://bitbucket.org/djtt/fake_therm_w1_slave/src/master/
Author: Ted van Roon
Author-email: tvanroon@gmail.com
License: UNKNOWN
Platform: UNKNOWN
Classifier: Programming Language :: Python :: 3
Classifier: License :: OSI Approved :: GNU General Public License v3 (GPLv3)
Classifier: Operating System :: OS Independent
Requires-Python: >=3
